listener/__init__.py
listener/listener.py
py_message_listener-0.2.dist-info/LICENSE
py_message_listener-0.2.dist-info/WHEEL
py_message_listener-0.2.dist-info/METADATA
py_message_listener-0.2.dist-info/RECORD
