Metadata-Version: 2.1
Name: py-message-listener
Version: 0.2
Summary: sqs message listener using boto3
License: MIT
Author: Raju Komati
Author-email: komatiraju032@gmail.com
Requires-Python: >=3.7,<4.0
Classifier: License :: OSI Approved :: MIT License
Classifier: Programming Language :: Python :: 3
Classifier: Programming Language :: Python :: 3.10
Classifier: Programming Language :: Python :: 3.7
Classifier: Programming Language :: Python :: 3.8
Classifier: Programming Language :: Python :: 3.9
Requires-Dist: boto3 (>=1.24.7,<2.0.0)
